common_module/NotionAPI.py
common_module/Task.py
common_module/TodoistAPI.py
common_module/User.py
common_module/__init__.py
common_library-0.1.1.dist-info/METADATA
common_library-0.1.1.dist-info/WHEEL
common_library-0.1.1.dist-info/top_level.txt
common_library-0.1.1.dist-info/RECORD
