Metadata-Version: 2.1
Name: common-library
Version: 0.1.1
Summary: UNKNOWN
Home-page: UNKNOWN
Author: UNKNOWN
Author-email: UNKNOWN
License: UNKNOWN
Platform: UNKNOWN
Requires-Dist: python-dateutil
Requires-Dist: google-cloud-bigquery
